ArubaCloud/PyArubaAPI.py
ArubaCloud/__init__.py
ArubaCloud/ReverseDns/ReverseDns.py
ArubaCloud/ReverseDns/__init__.py
ArubaCloud/ReverseDns/Requests/GetReverseDns.py
ArubaCloud/ReverseDns/Requests/SetEnqueueResetReverseDns.py
ArubaCloud/ReverseDns/Requests/SetEnqueueSetReverseDns.py
ArubaCloud/ReverseDns/Requests/_BaseReverseDns.py
ArubaCloud/ReverseDns/Requests/__init__.py
ArubaCloud/base/Errors.py
ArubaCloud/base/__init__.py
ArubaCloud/base/logsystem.py
ArubaCloud/base/vm.py
ArubaCloud/helper/__init__.py
ArubaCloud/objects/Scheduled.py
ArubaCloud/objects/Templates.py
ArubaCloud/objects/__init__.py
ArubaCloud/objects/VmTypes/__init__.py
pyArubaCloud-0.7.12.dist-info/LICENSE.txt
pyArubaCloud-0.7.12.dist-info/METADATA
pyArubaCloud-0.7.12.dist-info/WHEEL
pyArubaCloud-0.7.12.dist-info/top_level.txt
pyArubaCloud-0.7.12.dist-info/RECORD
