Metadata-Version: 2.1
Name: pyArubaCloud
Version: 0.7.12
Summary: Python Interface to interact with ArubaCloud IaaS Service.
Home-page: https://github.com/Arubacloud/pyArubaCloud
Author: Aruba S.p.A.
Author-email: luca.lasagni@staff.aruba.it
License: Apache License, Version 2.0
Keywords: arubacloud.com cloud.it Cloud IaaS Api
Platform: UNKNOWN
Classifier: Development Status :: 4 - Beta
Classifier: Intended Audience :: Developers
Classifier: Intended Audience :: Information Technology
Classifier: Intended Audience :: System Administrators
Classifier: License :: OSI Approved :: Apache Software License
Classifier: Operating System :: OS Independent
Classifier: Programming Language :: Python :: 2.7
Classifier: Programming Language :: Python :: 3.6
Classifier: Topic :: Software Development :: Libraries :: Python Modules
Classifier: Topic :: Utilities
Requires-Dist: requests (>=2.4.2)
Requires-Dist: jsonpickle
